opentelemetry/ext/__init__.py
opentelemetry/ext/honeycomb/__init__.py
opentelemetry/ext/honeycomb/test_suite.py
opentelemetry_ext_honeycomb-1.3.0.dist-info/LICENSE
opentelemetry_ext_honeycomb-1.3.0.dist-info/WHEEL
opentelemetry_ext_honeycomb-1.3.0.dist-info/METADATA
opentelemetry_ext_honeycomb-1.3.0.dist-info/RECORD
