Metadata-Version: 2.1
Name: opentelemetry-ext-honeycomb
Version: 1.3.0
Summary: OpenTelemetry plugins for Honeycomb
License: Apache-2.0
Author: Honeycomb Authors
Author-email: solutions@honeycomb.io
Requires-Python: >=3.6
Classifier: Development Status :: 3 - Alpha
Classifier: Intended Audience :: Developers
Classifier: License :: OSI Approved :: Apache Software License
Classifier: Programming Language :: Python
Classifier: Programming Language :: Python :: 3
Classifier: Programming Language :: Python :: 3.5
Classifier: Programming Language :: Python :: 3.6
Classifier: Programming Language :: Python :: 3.7
Classifier: Programming Language :: Python :: 3.8
Classifier: Programming Language :: Python :: 3.9
Requires-Dist: libhoney (>=1.10.0)
Requires-Dist: opentelemetry-api (==1.3.0)
Requires-Dist: opentelemetry-sdk (==1.3.0)
